rubecula/__init__.py
rubecula/_autoreload.py
rubecula/config.py
rubecula/expose.py
rubecula/injection.py
rubecula/logging.py
rubecula/server.py
rubecula/web.py
rubecula/ws.py
rubecula-0.1.2.dist-info/METADATA
rubecula-0.1.2.dist-info/WHEEL
rubecula-0.1.2.dist-info/top_level.txt
rubecula-0.1.2.dist-info/RECORD
