Metadata-Version: 2.1
Name: rubecula
Version: 0.1.2
Summary: UNKNOWN
License: UNKNOWN
Platform: UNKNOWN
Requires-Dist: twisted
Requires-Dist: autobahn
Requires-Dist: requests
Requires-Dist: pyopenssl
Requires-Dist: service-identity
Requires-Dist: pyyaml
Requires-Dist: jinja2
Requires-Dist: andi
Requires-Dist: rich
